awesome_table/__init__.py
awesome_table/column/__init__.py
awesome_table/frontend/build/asset-manifest.json
awesome_table/frontend/build/bootstrap.min.css
awesome_table/frontend/build/index.html
awesome_table/frontend/build/precache-manifest.37098fb026636865fdd2da13d2dba52f.js
awesome_table/frontend/build/service-worker.js
awesome_table/frontend/build/static/css/2.2515e1bc.chunk.css
awesome_table/frontend/build/static/css/2.2515e1bc.chunk.css.map
awesome_table/frontend/build/static/js/2.3a01e3d0.chunk.js
awesome_table/frontend/build/static/js/2.3a01e3d0.chunk.js.LICENSE.txt
awesome_table/frontend/build/static/js/2.3a01e3d0.chunk.js.map
awesome_table/frontend/build/static/js/main.b1c2cc97.chunk.js
awesome_table/frontend/build/static/js/main.b1c2cc97.chunk.js.map
awesome_table/frontend/build/static/js/runtime-main.11ec9aca.js
awesome_table/frontend/build/static/js/runtime-main.11ec9aca.js.map
awesome_table/frontend/build/static/media/fa-brands-400.ee91e640.woff2
awesome_table/frontend/build/static/media/fa-brands-400.f34b6a2a.ttf
awesome_table/frontend/build/static/media/fa-regular-400.65e80529.ttf
awesome_table/frontend/build/static/media/fa-regular-400.82bafee9.woff2
awesome_table/frontend/build/static/media/fa-solid-900.52afeb7a.ttf
awesome_table/frontend/build/static/media/fa-solid-900.57b380d2.woff2
awesome_table/frontend/build/static/media/fa-v4compatibility.43044320.woff2
awesome_table/frontend/build/static/media/fa-v4compatibility.9d6f359a.ttf
streamlit_awesome_table-0.0.3.dist-info/LICENSE
streamlit_awesome_table-0.0.3.dist-info/METADATA
streamlit_awesome_table-0.0.3.dist-info/WHEEL
streamlit_awesome_table-0.0.3.dist-info/top_level.txt
streamlit_awesome_table-0.0.3.dist-info/RECORD
