Metadata-Version: 2.1
Name: streamlit-awesome-table
Version: 0.0.3
Summary: Awesome Table is a component to display a table in Streamlit with search and order.
Home-page: https://github.com/caiodearaujo/streamlit-awesome-table
Author: Caio Fábio de Araujo
Author-email: caiofaar@gmail.com
License: MIT
Platform: UNKNOWN
Requires-Python: >=3.6
License-File: LICENSE
Requires-Dist: streamlit (>=0.63)
Requires-Dist: pandas
